[{"withdrawal_id":"WIT2F76DPX8DUFX5RU282UZ","status":"pending","user_id":"MTcwOTM3NDE4Mg==","num":"40","TRX_code":"sdfsdfdsfdfds","date_of_withdrawal":"Mar 16 2024 21:23:01","tymd":1710624181},{"withdrawal_id":"WITNG5DATAN571U5QXUOGTD","status":"declined","user_id":"MTcwOTM3NDE4Mg==","num":"500","TRX_code":"sdfsdfdsfdfds","date_of_withdrawal":"Mar 16 2024 21:23:34","tymd":1710624214},{"withdrawal_id":"WITM3NDT1F18R78UQHWHENA","status":"pending","user_id":"MTcwOTM3NDE4Mg==","num":"42","TRX_code":"nccceee","date_of_withdrawal":"Mar 16 2024 21:25:15","tymd":1710624315},{"withdrawal_id":"WITE177TALAALVOT1VNV5GD","status":"successful","user_id":"MTcwOTM3NDE4Mg==","num":"65","TRX_code":"ffdfdfg","date_of_withdrawal":"Mar 16 2024 21:26:10","tymd":1710624370}]